notebooklm_mcp/__init__.py
notebooklm_mcp/api_client.py
notebooklm_mcp/auth.py
notebooklm_mcp/auth_cli.py
notebooklm_mcp/constants.py
notebooklm_mcp/server.py
notebooklm_mcp_server-0.1.15.dist-info/METADATA
notebooklm_mcp_server-0.1.15.dist-info/WHEEL
notebooklm_mcp_server-0.1.15.dist-info/entry_points.txt
notebooklm_mcp_server-0.1.15.dist-info/licenses/LICENSE
notebooklm_mcp_server-0.1.15.dist-info/RECORD
