Metadata-Version: 2.4
Name: notebooklm-mcp-server
Version: 0.1.15
Summary: MCP server for NotebookLM (notebooklm.google.com)
Author: Jacob Ben-David
License-Expression: MIT
License-File: LICENSE
Keywords: ai,google,mcp,notebooklm,research
Classifier: Development Status :: 3 - Alpha
Classifier: Intended Audience :: Developers
Classifier: License :: OSI Approved :: MIT License
Classifier: Programming Language :: Python :: 3.11
Classifier: Programming Language :: Python :: 3.12
Requires-Python: >=3.11
Requires-Dist: fastmcp>=0.1.0
Requires-Dist: httpx>=0.27.0
Requires-Dist: websocket-client>=1.6.0
Provides-Extra: dev
Requires-Dist: pytest-asyncio>=0.23.0; extra == 'dev'
Requires-Dist: pytest>=8.0.0; extra == 'dev'
